osm_roads/__init__.py
osm_roads/osm_roads.py
osm_roads-0.24.dist-info/LICENSE
osm_roads-0.24.dist-info/METADATA
osm_roads-0.24.dist-info/WHEEL
osm_roads-0.24.dist-info/top_level.txt
osm_roads-0.24.dist-info/RECORD
