Metadata-Version: 2.1
Name: osm-roads
Version: 0.24
Summary: UNKNOWN
Home-page: https://github.com/sahyagiri/osm_roads
Author: Gireesan Namboothiri
Author-email: sahyagiri@gmail.com
License: UNKNOWN
Project-URL: Bug Tracker, https://github.com/sahyagiri/osm_roads/issues
Keywords: openstreetmap,map matching,pbf,trie,geohash
Platform: UNKNOWN
Classifier: Programming Language :: Python :: 3
Classifier: License :: OSI Approved :: MIT License
Classifier: Operating System :: OS Independent
Requires-Python: >=3.6
License-File: LICENSE
Requires-Dist: datrie
Requires-Dist: geojson
Requires-Dist: osmium
Requires-Dist: python-geohash
Requires-Dist: turfpy
Requires-Dist: h5py
